[
  {
    "timestamp": "2025-06-02T17:07:23.660370",
    "job_name": "sample_job",
    "destination": "email",
    "success": true,
    "details": {
      "recipients": [
        "ops@example.com"
      ]
    }
  },
  {
    "timestamp": "2025-06-02T17:07:23.661311",
    "job_name": "sample_job",
    "destination": "file",
    "success": false,
    "details": {
      "error": "Object of type datetime is not JSON serializable"
    }
  },
  {
    "timestamp": "2025-06-02T17:08:31.384398",
    "job_name": "sample_job",
    "destination": "email",
    "success": true,
    "details": {
      "recipients": [
        "ops@example.com"
      ]
    }
  },
  {
    "timestamp": "2025-06-02T17:08:31.385174",
    "job_name": "sample_job",
    "destination": "file",
    "success": true,
    "details": {
      "path": "./exports/sample_job/"
    }
  },
  {
    "timestamp": "2025-06-02T17:57:35.613050",
    "job_name": "sample_job",
    "destination": "email",
    "success": true,
    "details": {
      "recipients": [
        "ops@example.com"
      ]
    }
  },
  {
    "timestamp": "2025-06-02T17:57:35.613948",
    "job_name": "sample_job",
    "destination": "file",
    "success": true,
    "details": {
      "path": "./exports/sample_job/"
    }
  },
  {
    "timestamp": "2025-06-03T19:05:34.245877",
    "job_name": "sample_job",
    "destination": "email",
    "success": true,
    "details": {
      "recipients": [
        "ops@example.com"
      ]
    }
  },
  {
    "timestamp": "2025-06-03T19:05:34.246754",
    "job_name": "sample_job",
    "destination": "file",
    "success": true,
    "details": {
      "path": "./exports/sample_job/"
    }
  },
  {
    "timestamp": "2025-06-03T19:26:15.917665",
    "job_name": "sample_job",
    "destination": "email",
    "success": true,
    "details": {
      "recipients": [
        "ops@example.com"
      ]
    }
  },
  {
    "timestamp": "2025-06-03T19:26:15.918652",
    "job_name": "sample_job",
    "destination": "file",
    "success": true,
    "details": {
      "path": "./exports/sample_job/"
    }
  },
  {
    "timestamp": "2025-06-03T19:35:33.285948",
    "job_name": "sample_job",
    "destination": "email",
    "success": true,
    "details": {
      "recipients": [
        "ops@example.com"
      ]
    }
  },
  {
    "timestamp": "2025-06-03T19:35:33.286942",
    "job_name": "sample_job",
    "destination": "file",
    "success": true,
    "details": {
      "path": "./exports/sample_job/"
    }
  },
  {
    "timestamp": "2025-06-03T19:38:00.482478",
    "job_name": "sample_job",
    "destination": "email",
    "success": true,
    "details": {
      "recipients": [
        "ops@example.com"
      ]
    }
  },
  {
    "timestamp": "2025-06-03T19:38:00.483519",
    "job_name": "sample_job",
    "destination": "file",
    "success": true,
    "details": {
      "path": "./exports/sample_job/"
    }
  },
  {
    "timestamp": "2025-06-03T19:45:18.899151",
    "job_name": "sample_job",
    "destination": "email",
    "success": true,
    "details": {
      "recipients": [
        "ops@example.com"
      ]
    }
  },
  {
    "timestamp": "2025-06-03T19:45:18.900139",
    "job_name": "sample_job",
    "destination": "file",
    "success": true,
    "details": {
      "path": "./exports/sample_job/"
    }
  },
  {
    "timestamp": "2025-06-03T19:49:46.064930",
    "job_name": "sample_job",
    "destination": "email",
    "success": true,
    "details": {
      "recipients": [
        "ops@example.com"
      ]
    }
  },
  {
    "timestamp": "2025-06-03T19:49:46.065942",
    "job_name": "sample_job",
    "destination": "file",
    "success": true,
    "details": {
      "path": "./exports/sample_job/"
    }
  },
  {
    "timestamp": "2025-06-03T19:56:12.747528",
    "job_name": "sample_job",
    "destination": "email",
    "success": true,
    "details": {
      "recipients": [
        "ops@example.com"
      ]
    }
  },
  {
    "timestamp": "2025-06-03T19:56:12.748501",
    "job_name": "sample_job",
    "destination": "file",
    "success": true,
    "details": {
      "path": "./exports/sample_job/"
    }
  },
  {
    "timestamp": "2025-06-03T19:56:31.941038",
    "job_name": "sample_job",
    "destination": "email",
    "success": true,
    "details": {
      "recipients": [
        "ops@example.com"
      ]
    }
  },
  {
    "timestamp": "2025-06-03T19:56:31.942061",
    "job_name": "sample_job",
    "destination": "file",
    "success": true,
    "details": {
      "path": "./exports/sample_job/"
    }
  },
  {
    "timestamp": "2025-06-03T20:01:20.685914",
    "job_name": "sample_job",
    "destination": "email",
    "success": true,
    "details": {
      "recipients": [
        "johanvanerkel@gmail.com",
        "jovanerkel@gmail.com"
      ]
    }
  },
  {
    "timestamp": "2025-06-03T20:01:20.687002",
    "job_name": "sample_job",
    "destination": "file",
    "success": true,
    "details": {
      "path": "./exports/sample_job/"
    }
  },
  {
    "timestamp": "2025-06-04T06:52:37.844706",
    "job_name": "sample_job",
    "destination": "email",
    "success": true,
    "details": {
      "recipients": [
        "johanvanerkel@gmail.com",
        "jovanerkel@gmail.com"
      ]
    }
  },
  {
    "timestamp": "2025-06-04T06:52:37.846194",
    "job_name": "sample_job",
    "destination": "file",
    "success": true,
    "details": {
      "path": "./exports/sample_job/"
    }
  },
  {
    "timestamp": "2025-06-04T07:00:32.580595",
    "job_name": "sample_job",
    "destination": "email",
    "success": true,
    "details": {
      "recipients": [
        "johanvanerkel@gmail.com",
        "jovanerkel@gmail.com"
      ]
    }
  },
  {
    "timestamp": "2025-06-04T07:00:32.582454",
    "job_name": "sample_job",
    "destination": "file",
    "success": true,
    "details": {
      "path": "./exports/sample_job/"
    }
  },
  {
    "timestamp": "2025-06-04T07:03:42.084658",
    "job_name": "sample_job",
    "destination": "email",
    "success": true,
    "details": {
      "recipients": [
        "johanvanerkel@gmail.com",
        "jovanerkel@gmail.com"
      ]
    }
  },
  {
    "timestamp": "2025-06-04T07:03:42.086240",
    "job_name": "sample_job",
    "destination": "file",
    "success": true,
    "details": {
      "path": "./exports/sample_job/"
    }
  },
  {
    "timestamp": "2025-06-04T07:03:58.755301",
    "job_name": "sample_job",
    "destination": "email",
    "success": true,
    "details": {
      "recipients": [
        "johanvanerkel@gmail.com",
        "jovanerkel@gmail.com"
      ]
    }
  },
  {
    "timestamp": "2025-06-04T07:03:58.756698",
    "job_name": "sample_job",
    "destination": "file",
    "success": true,
    "details": {
      "path": "./exports/sample_job/"
    }
  },
  {
    "timestamp": "2025-06-07T12:02:58.697163",
    "job_name": "Data Entry Specialist",
    "destination": "log",
    "success": false,
    "details": {
      "error": "Unknown export destination: log"
    }
  },
  {
    "timestamp": "2025-06-07T12:02:58.698364",
    "job_name": "Data Entry Specialist",
    "destination": "file",
    "success": false,
    "details": {
      "error": "FileExporter.__init__() missing 1 required positional argument: 'job_id'"
    }
  },
  {
    "timestamp": "2025-06-07T12:12:41.157773",
    "job_name": "Data Entry Specialist",
    "destination": "log",
    "success": false,
    "details": {
      "error": "Unknown export destination: log"
    }
  },
  {
    "timestamp": "2025-06-07T12:12:41.158880",
    "job_name": "Data Entry Specialist",
    "destination": "file",
    "success": false,
    "details": {
      "error": "Object of type datetime is not JSON serializable"
    }
  },
  {
    "timestamp": "2025-06-07T12:16:50.016767",
    "job_name": "Data Entry Specialist",
    "destination": "log",
    "success": true,
    "details": {
      "details": {}
    }
  },
  {
    "timestamp": "2025-06-07T12:16:50.018138",
    "job_name": "Data Entry Specialist",
    "destination": "file",
    "success": true,
    "details": {
      "details": {}
    }
  },
  {
    "timestamp": "2025-06-07T12:18:27.453587",
    "job_name": "Data Entry Specialist",
    "destination": "log",
    "success": true,
    "details": {
      "details": {}
    }
  },
  {
    "timestamp": "2025-06-07T12:18:27.454948",
    "job_name": "Data Entry Specialist",
    "destination": "file",
    "success": true,
    "details": {
      "details": {}
    }
  },
  {
    "timestamp": "2025-06-07T13:53:51.116235",
    "job_name": "sample_job",
    "destination": "email",
    "success": false,
    "details": {
      "error": "MailgunExporter() takes no arguments"
    }
  },
  {
    "timestamp": "2025-06-07T13:53:51.118259",
    "job_name": "sample_job",
    "destination": "file",
    "success": true,
    "details": {
      "details": {
        "directory": "./exports/sample_job/"
      }
    }
  },
  {
    "timestamp": "2025-06-07T13:58:26.559906",
    "job_name": "sample_job",
    "destination": "email",
    "success": false,
    "details": {
      "error": "MailgunExporter.export() takes 2 positional arguments but 3 were given"
    }
  },
  {
    "timestamp": "2025-06-07T13:58:26.564059",
    "job_name": "sample_job",
    "destination": "file",
    "success": true,
    "details": {
      "details": {
        "directory": "./exports/sample_job/"
      }
    }
  },
  {
    "timestamp": "2025-06-07T13:59:40.245606",
    "job_name": "sample_job",
    "destination": "email",
    "success": true,
    "details": {
      "details": {
        "recipients": [
          "johanvanerkel@gmail.com",
          "jovanerkel@gmail.com"
        ],
        "subject": "Ghost Employee Summary - Sample Job",
        "message": "Here is your daily summary:\n\nThe client has requested a weekly performance report. The deadline for this task is the upcoming Friday and it has been assigned to Lisa.\n\nTasks:\n- Add Alice to CRM (Due: N/A, Assigned: None)"
      }
    }
  },
  {
    "timestamp": "2025-06-07T13:59:40.248778",
    "job_name": "sample_job",
    "destination": "file",
    "success": false,
    "details": {
      "error": "FileExporter.export() missing 1 required positional argument: 'config'"
    }
  },
  {
    "timestamp": "2025-06-07T14:01:50.456799",
    "job_name": "sample_job",
    "destination": "email",
    "success": true,
    "details": {
      "details": {
        "recipients": [
          "johanvanerkel@gmail.com",
          "jovanerkel@gmail.com"
        ],
        "subject": "Ghost Employee Summary - Sample Job",
        "message": "Here is your daily summary:\n\nThe client has requested a weekly performance report which is due by next Friday. The task has been assigned to Lisa.\n\nTasks:\n- Add Alice to CRM (Due: N/A, Assigned: None)"
      }
    }
  },
  {
    "timestamp": "2025-06-07T14:01:50.460311",
    "job_name": "sample_job",
    "destination": "file",
    "success": true,
    "details": {
      "details": {
        "directory": "./exports/sample_job/"
      }
    }
  },
  {
    "timestamp": "2025-06-07T14:04:18.165799",
    "job_name": "sample_job",
    "destination": "email",
    "success": true,
    "details": {
      "details": {
        "recipients": [
          "johanvanerkel@gmail.com",
          "jovanerkel@gmail.com"
        ],
        "subject": "Ghost Employee Summary - Sample Job",
        "message": "Here is your daily summary:\n\nThe client has requested a weekly performance report, which is due by next Friday. The task has been assigned to Lisa.\n\nTasks:\n- Add Alice to CRM (Due: N/A, Assigned: None)"
      }
    }
  },
  {
    "timestamp": "2025-06-07T14:04:18.170078",
    "job_name": "sample_job",
    "destination": "file",
    "success": true,
    "details": {
      "details": {
        "directory": "./exports/sample_job/"
      }
    }
  },
  {
    "timestamp": "2025-06-07T14:05:49.515502",
    "job_name": "sample_job",
    "destination": "email",
    "success": true,
    "details": {
      "details": {
        "recipients": [
          "johanvanerkel@gmail.com",
          "jovanerkel@gmail.com"
        ],
        "subject": "Ghost Employee Summary - Sample Job",
        "message": "Here is your daily summary:\n\nThe client has requested a weekly performance report, which is due by next Friday. The task has been assigned to Lisa.\n\nTasks:\n- Add Alice to CRM (Due: N/A, Assigned: None)"
      }
    }
  },
  {
    "timestamp": "2025-06-07T14:05:49.518603",
    "job_name": "sample_job",
    "destination": "file",
    "success": true,
    "details": {
      "details": {
        "directory": "./exports/sample_job/"
      }
    }
  },
  {
    "timestamp": "2025-06-07T14:08:49.210623",
    "job_name": "sample_job",
    "destination": "email",
    "success": true,
    "details": {
      "details": {
        "recipients": [
          "johanvanerkel@gmail.com",
          "jovanerkel@gmail.com"
        ],
        "subject": "Ghost Employee Summary - Sample Job",
        "message": "Here is your daily summary:\n\nThe client has requested a weekly performance report which is due by next Friday. The task has been assigned to Lisa.\n\nTasks:\n- Update contact Alice (Due: N/A, Assigned: None)"
      }
    }
  },
  {
    "timestamp": "2025-06-07T14:08:49.212164",
    "job_name": "sample_job",
    "destination": "file",
    "success": true,
    "details": {
      "details": {
        "directory": "./exports/sample_job/"
      }
    }
  },
  {
    "timestamp": "2025-06-07T14:39:27.135217",
    "job_name": "crm_ops_job",
    "destination": "email",
    "success": true,
    "details": {
      "details": {
        "recipients": [
          "johanvanerkel@gmail.com"
        ],
        "subject": "CRM Summary - Ghost Employee",
        "message": "Daily CRM update:\n\nThe file instructs to add a new contact named Alice to the Customer Relationship Management (CRM) system. Alice is the new liaison at Acme Corp. Additionally, the file requests an update to the contact details of Bob, specifically a change in his phone number.\n\nTasks:\n- Add a new contact named Alice to the Customer Relationship Management (CRM) system (Due: N/A, Assigned: None)\n- Update the contact details of Bob, specifically a change in his phone number (Due: N/A, Assigned: None)"
      }
    }
  },
  {
    "timestamp": "2025-06-07T14:39:27.137108",
    "job_name": "crm_ops_job",
    "destination": "file",
    "success": true,
    "details": {
      "details": {
        "directory": "./exports/crm_ops_job/"
      }
    }
  },
  {
    "timestamp": "2025-06-07T14:51:49.111743",
    "job_name": "crm_ops_job",
    "destination": "email",
    "success": true,
    "details": {
      "details": {
        "recipients": [
          "johanvanerkel@gmail.com"
        ],
        "subject": "CRM Summary - Ghost Employee",
        "message": "Daily CRM update:\n\nThe file instructs to add Alice as a new contact in the Customer Relationship Management (CRM) system. She is the new liaison at Acme Corp. Additionally, it is necessary to update the contact details of Bob due to a change in his phone number.\n\nTasks:\n- Add Alice as a new contact in the Customer Relationship Management (CRM) system (Due: N/A, Assigned: None)\n- Update the contact details of Bob due to a change in his phone number (Due: N/A, Assigned: None)"
      }
    }
  },
  {
    "timestamp": "2025-06-07T14:51:49.113534",
    "job_name": "crm_ops_job",
    "destination": "file",
    "success": true,
    "details": {
      "details": {
        "directory": "./exports/crm_ops_job/"
      }
    }
  },
  {
    "timestamp": "2025-06-07T14:59:14.722113",
    "job_name": "crm_ops_job",
    "destination": "email",
    "success": true,
    "details": {
      "details": {
        "recipients": [
          "johanvanerkel@gmail.com"
        ],
        "subject": "CRM Summary - Ghost Employee",
        "message": "Daily CRM update:\n\nThe file instructs to add Alice as a new contact in the Customer Relationship Management system, specifying her as the new point of contact at Acme Corp. It also requests an update to Bob's contact information due to a change in his phone number.\n\nTasks:\n- Add Alice as a new contact in the Customer Relationship Management system and specify her as the new point of contact at Acme Corp (Due: N/A, Assigned: None)\n- Update Bob's contact information in the Customer Relationship Management system due to a change in his phone number (Due: N/A, Assigned: None)"
      }
    }
  },
  {
    "timestamp": "2025-06-07T14:59:14.725413",
    "job_name": "crm_ops_job",
    "destination": "file",
    "success": true,
    "details": {
      "details": {
        "directory": "./exports/crm_ops_job/"
      }
    }
  },
  {
    "timestamp": "2025-06-07T15:05:31.583600",
    "job_name": "crm_ops_job",
    "destination": "email",
    "success": true,
    "details": {
      "details": {
        "recipients": [
          "johanvanerkel@gmail.com"
        ],
        "subject": "CRM Summary - Ghost Employee",
        "message": "Daily CRM update:\n\nThe file instructs to add a new contact named Alice to the Customer Relationship Management system, who is the new liaison at Acme Corp. It also directs to update the contact details of Bob due to a change in his phone number.\n\nTasks:\n- Add a new contact named Alice to the Customer Relationship Management system (Due: N/A, Assigned: None)\n- Update the contact details of Bob due to a change in his phone number (Due: N/A, Assigned: None)"
      }
    }
  },
  {
    "timestamp": "2025-06-07T15:05:31.586747",
    "job_name": "crm_ops_job",
    "destination": "file",
    "success": true,
    "details": {
      "details": {
        "directory": "./exports/crm_ops_job/"
      }
    }
  },
  {
    "timestamp": "2025-06-07T15:06:59.297271",
    "job_name": "crm_ops_job",
    "destination": "email",
    "success": true,
    "details": {
      "details": {
        "recipients": [
          "johanvanerkel@gmail.com"
        ],
        "subject": "CRM Summary - Ghost Employee",
        "message": "Daily CRM update:\n\nThe file instructs to add Alice as a new contact in the Customer Relationship Management (CRM) system, noting that she is the new liaison at Acme Corp. It also requests an update to Bob's contact information, specifically a change in his phone number.\n\nTasks:\n- Add Alice as a new contact in the CRM system (Due: N/A, Assigned: None)\n- Note that Alice is the new liaison at Acme Corp (Due: N/A, Assigned: None)\n- Update Bob's contact information in the CRM system (Due: N/A, Assigned: None)\n- Change Bob's phone number in the CRM system (Due: N/A, Assigned: None)"
      }
    }
  },
  {
    "timestamp": "2025-06-07T15:06:59.301622",
    "job_name": "crm_ops_job",
    "destination": "file",
    "success": true,
    "details": {
      "details": {
        "directory": "./exports/crm_ops_job/"
      }
    }
  },
  {
    "timestamp": "2025-06-07T15:12:01.600706",
    "job_name": "crm_ops_job",
    "destination": "email",
    "success": true,
    "details": {
      "details": {
        "recipients": [
          "johanvanerkel@gmail.com"
        ],
        "subject": "CRM Summary - Ghost Employee",
        "message": "Daily CRM update:\n\nThe file instructs to add a new contact, Alice, to the Customer Relationship Management system. Alice is the new liaison at Acme Corp. The file also requests an update to the contact details of Bob, specifically a change in his phone number.\n\nTasks:\n- Add a new contact, Alice, to the Customer Relationship Management system (Due: N/A, Assigned: None)\n- Update the contact details of Bob, specifically a change in his phone number (Due: N/A, Assigned: None)"
      }
    }
  },
  {
    "timestamp": "2025-06-07T15:12:01.605817",
    "job_name": "crm_ops_job",
    "destination": "file",
    "success": true,
    "details": {
      "details": {
        "directory": "./exports/crm_ops_job/"
      }
    }
  },
  {
    "timestamp": "2025-06-07T15:19:47.425610",
    "job_name": "crm_ops_job",
    "destination": "email",
    "success": true,
    "details": {
      "details": {
        "recipients": [
          "johanvanerkel@gmail.com"
        ],
        "subject": "CRM Summary - Ghost Employee",
        "message": "Daily CRM update:\n\nPlease add Alice as a new contact in the CRM, she is now our main liaison at Acme Corp. Additionally, Bob's contact information requires updating due to a change in his phone number.\n\nTasks:\n- Add Alice as a new contact in the CRM, with her role as main liaison at Acme Corp (Due: N/A, Assigned: None)\n- Update Bob's contact information in the CRM due to a change in his phone number (Due: N/A, Assigned: None)"
      }
    }
  },
  {
    "timestamp": "2025-06-07T15:19:47.427878",
    "job_name": "crm_ops_job",
    "destination": "file",
    "success": true,
    "details": {
      "details": {
        "directory": "./exports/crm_ops_job/"
      }
    }
  },
  {
    "timestamp": "2025-06-07T15:31:49.966519",
    "job_name": "crm_ops_job",
    "destination": "email",
    "success": true,
    "details": {
      "details": {
        "recipients": [
          "johanvanerkel@gmail.com"
        ],
        "subject": "CRM Summary - Ghost Employee",
        "message": "Daily CRM update:\n\nPlease add Alice as a new contact in the CRM, representing Acme Corp. Additionally, update Bob's contact information due to a change in his phone number.\n\nTasks:\n- Add Alice as a new contact in the CRM (Due: N/A, Assigned: unknown)\n- Update Bob's contact information due to a change in his phone number (Due: N/A, Assigned: unknown)\n- Assign Alice to represent Acme Corp (Due: N/A, Assigned: unknown)"
      }
    }
  },
  {
    "timestamp": "2025-06-07T15:31:49.970620",
    "job_name": "crm_ops_job",
    "destination": "file",
    "success": true,
    "details": {
      "details": {
        "directory": "./exports/crm_ops_job/"
      }
    }
  },
  {
    "timestamp": "2025-06-07T15:35:16.429547",
    "job_name": "crm_ops_job",
    "destination": "email",
    "success": true,
    "details": {
      "details": {
        "recipients": [
          "johanvanerkel@gmail.com"
        ],
        "subject": "CRM Summary - Ghost Employee",
        "message": "Daily CRM update:\n\nPlease add a new contact, Alice, to the CRM. She is now our main liaison at Acme Corp. Additionally, Bob's contact information needs to be updated due to a change in his phone number.\n\nTasks:\n- Add a new contact, Alice, to the CRM (Due: N/A, Assigned: unknown)\n- Update Alice's role to main liaison at Acme Corp (Due: N/A, Assigned: unknown)\n- Update Bob's contact information due to a change in his phone number (Due: N/A, Assigned: unknown)"
      }
    }
  },
  {
    "timestamp": "2025-06-07T15:35:16.434778",
    "job_name": "crm_ops_job",
    "destination": "file",
    "success": true,
    "details": {
      "details": {
        "directory": "./exports/crm_ops_job/"
      }
    }
  },
  {
    "timestamp": "2025-06-07T15:39:23.532065",
    "job_name": "crm_ops_job",
    "destination": "email",
    "success": true,
    "details": {
      "details": {
        "recipients": [
          "johanvanerkel@gmail.com"
        ],
        "subject": "CRM Summary - Ghost Employee",
        "message": "Daily CRM update:\n\nPlease add Alice as a new contact in the CRM, representing our new liaison at Acme Corp. Additionally, Bob's contact information needs to be updated due to a change in his phone number.\n\nTasks:\n- Add Alice as a new contact in the CRM (Due: N/A, Assigned: unknown)\n- Update Bob's contact information in the CRM (Due: N/A, Assigned: unknown)\n- Assign Alice as the new liaison for Acme Corp in the CRM (Due: N/A, Assigned: unknown)"
      }
    }
  },
  {
    "timestamp": "2025-06-07T15:39:23.535050",
    "job_name": "crm_ops_job",
    "destination": "file",
    "success": true,
    "details": {
      "details": {
        "directory": "./exports/crm_ops_job/"
      }
    }
  },
  {
    "timestamp": "2025-06-07T15:46:53.040352",
    "job_name": "crm_ops_job",
    "destination": "email",
    "success": true,
    "details": {
      "details": {
        "recipients": [
          "johanvanerkel@gmail.com"
        ],
        "subject": "CRM Summary - Ghost Employee",
        "message": "Daily CRM update:\n\nPlease add Alice as a new contact in the CRM, she is now our main liaison at Acme Corp. Additionally, amend Bob's contact details to reflect his new phone number.\n\nTasks:\n- Add Alice as a new contact in the CRM (Due: N/A, Assigned: None)\n- Amend Bob's contact details to reflect his new phone number (Due: N/A, Assigned: None)"
      }
    }
  },
  {
    "timestamp": "2025-06-07T15:46:53.044439",
    "job_name": "crm_ops_job",
    "destination": "file",
    "success": true,
    "details": {
      "details": {
        "directory": "./exports/crm_ops_job/"
      }
    }
  },
  {
    "timestamp": "2025-06-07T15:48:51.913536",
    "job_name": "crm_ops_job",
    "destination": "email",
    "success": true,
    "details": {
      "details": {
        "recipients": [
          "johanvanerkel@gmail.com"
        ],
        "subject": "CRM Summary - Ghost Employee",
        "message": "Daily CRM update:\n\nPlease add Alice as a new contact in the CRM, representing our new liaison at Acme Corp. Additionally, update Bob's contact details to reflect his new phone number.\n\nTasks:\n- Add Alice as a new contact in the CRM (Due: N/A, Assigned: None)\n- Update Bob's contact details to reflect his new phone number (Due: N/A, Assigned: None)"
      }
    }
  },
  {
    "timestamp": "2025-06-07T15:48:51.918669",
    "job_name": "crm_ops_job",
    "destination": "file",
    "success": true,
    "details": {
      "details": {
        "directory": "./exports/crm_ops_job/"
      }
    }
  }
]